setup.py
distributions_exercise_5_pio/Binomialdistribution.py
distributions_exercise_5_pio/Gaussiandistribution.py
distributions_exercise_5_pio/Generaldistribution.py
distributions_exercise_5_pio/__init__.py
distributions_exercise_5_pio.egg-info/PKG-INFO
distributions_exercise_5_pio.egg-info/SOURCES.txt
distributions_exercise_5_pio.egg-info/dependency_links.txt
distributions_exercise_5_pio.egg-info/not-zip-safe
distributions_exercise_5_pio.egg-info/top_level.txt