Metadata-Version: 1.0
Name: distributions-exercise-5-pio
Version: 0.1
Summary: Gaussian distributions
Home-page: UNKNOWN
Author: Pio Korinth
Author-email: pio@kth.se
License: UNKNOWN
Platform: UNKNOWN
